datagrepper/__init__.py
datagrepper/app.py
datagrepper/default_config.py
datagrepper/docs/Makefile
datagrepper/docs/charts.rst
datagrepper/docs/conf.py
datagrepper/docs/contributing.rst
datagrepper/docs/datagrepper.png
datagrepper/docs/index.rst
datagrepper/docs/reference.rst
datagrepper/docs/release_notes.rst
datagrepper/docs/widget.rst
datagrepper/static/autoscroll.js
datagrepper/static/css/fedora-bootstrap-fonts.css
datagrepper/static/css/fonts/Bold/OpenSans-Bold.ttf
datagrepper/static/css/fonts/Bold/OpenSans-Bold.woff
datagrepper/static/css/fonts/Bold/OpenSans-Bold.woff2
datagrepper/static/css/fonts/Bold/hack-bold-webfont.ttf
datagrepper/static/css/fonts/Bold/hack-bold-webfont.woff
datagrepper/static/css/fonts/Bold/hack-bold-webfont.woff2
datagrepper/static/css/fonts/BoldItalic/OpenSans-BoldItalic.ttf
datagrepper/static/css/fonts/BoldItalic/OpenSans-BoldItalic.woff
datagrepper/static/css/fonts/BoldItalic/OpenSans-BoldItalic.woff2
datagrepper/static/css/fonts/BoldItalic/hack-bolditalic-webfont.ttf
datagrepper/static/css/fonts/BoldItalic/hack-bolditalic-webfont.woff
datagrepper/static/css/fonts/BoldItalic/hack-bolditalic-webfont.woff2
datagrepper/static/css/fonts/Italic/OpenSans-Italic.ttf
datagrepper/static/css/fonts/Italic/OpenSans-Italic.woff
datagrepper/static/css/fonts/Italic/OpenSans-Italic.woff2
datagrepper/static/css/fonts/Italic/hack-italic-webfont.ttf
datagrepper/static/css/fonts/Italic/hack-italic-webfont.woff
datagrepper/static/css/fonts/Italic/hack-italic-webfont.woff2
datagrepper/static/css/fonts/Light/OpenSans-Light.ttf
datagrepper/static/css/fonts/Light/OpenSans-Light.woff
datagrepper/static/css/fonts/Light/OpenSans-Light.woff2
datagrepper/static/css/fonts/LightItalic/OpenSans-LightItalic.ttf
datagrepper/static/css/fonts/LightItalic/OpenSans-LightItalic.woff
datagrepper/static/css/fonts/LightItalic/OpenSans-LightItalic.woff2
datagrepper/static/css/fonts/Regular/OpenSans-Regular.ttf
datagrepper/static/css/fonts/Regular/OpenSans-Regular.woff
datagrepper-1.1.0.dist-info/COPYING
datagrepper-1.1.0.dist-info/METADATA
datagrepper-1.1.0.dist-info/WHEEL
datagrepper-1.1.0.dist-info/RECORD
