Metadata-Version: 2.1
Name: datagrepper
Version: 1.1.0
Summary: A webapp to query datanommer
Home-page: https://github.com/fedora-infra/datagrepper
License: GPL-2.0-or-later
Author: Fedora Infrastructure
Author-email: admin@fedoraproject.org
Requires-Python: >=3.10,<4.0
Classifier: License :: OSI Approved :: GNU General Public License v2 or later (GPLv2+)
Classifier: Programming Language :: Python :: 3
Classifier: Programming Language :: Python :: 3.10
Classifier: Programming Language :: Python :: 3.11
Provides-Extra: deploy
Provides-Extra: schemas
Requires-Dist: Pygments (>=2.9.0,<3.0.0)
Requires-Dist: SQLAlchemy (>=1.4.0,<2.0.0)
Requires-Dist: anitya-schema ; extra == "schemas"
Requires-Dist: arrow (>=1.1.1,<2.0.0)
Requires-Dist: bodhi-messages ; extra == "schemas"
Requires-Dist: cffi (>=1.14.6,<2.0.0)
Requires-Dist: copr-messaging ; extra == "schemas"
Requires-Dist: datanommer.models (>=1.0.0,<2.0.0)
Requires-Dist: discourse2fedmsg-messages ; extra == "schemas"
Requires-Dist: docutils (>=0.16)
Requires-Dist: fedocal-messages ; extra == "schemas"
Requires-Dist: fedora-messaging (>=2.1.0)
Requires-Dist: fedora-messaging-the-new-hotness-schema ; extra == "schemas"
Requires-Dist: fedora-planet-messages ; extra == "schemas"
Requires-Dist: fedorainfra-ansible-messages ; extra == "schemas"
Requires-Dist: flask (>=2.0.1)
Requires-Dist: flask-healthz (>=0.0.3,<0.0.4)
Requires-Dist: gunicorn (>=20.0,<22.0.0) ; extra == "deploy"
Requires-Dist: mdapi-messages ; extra == "schemas"
Requires-Dist: moksha.common (>=1.2.5,<2.0.0)
Requires-Dist: noggin-messages ; extra == "schemas"
Requires-Dist: nuancier-messages ; extra == "schemas"
Requires-Dist: pagure-messages ; extra == "schemas"
Requires-Dist: psycopg2 (>=2.9.1,<3.0.0)
Requires-Dist: pygal (>=2.4.0)
Requires-Dist: python-dateutil (>=2.8.1,<3.0.0)
Project-URL: Repository, https://github.com/fedora-infra/datagrepper
